{
    "id": "e96cb526-bba2-42b9-b236-bc5d0b2a3900",
    "realm": "nethera",
    "notBefore": 0,
    "defaultSignatureAlgorithm": "RS256",
    "revokeRefreshToken": false,
    "refreshTokenMaxReuse": 0,
    "accessTokenLifespan": 300,
    "accessTokenLifespanForImplicitFlow": 900,
    "ssoSessionIdleTimeout": 1800,
    "ssoSessionMaxLifespan": 36000,
    "ssoSessionIdleTimeoutRememberMe": 0,
    "ssoSessionMaxLifespanRememberMe": 0,
    "offlineSessionIdleTimeout": 2592000,
    "offlineSessionMaxLifespanEnabled": false,
    "offlineSessionMaxLifespan": 5184000,
    "clientSessionIdleTimeout": 0,
    "clientSessionMaxLifespan": 0,
    "clientOfflineSessionIdleTimeout": 0,
    "clientOfflineSessionMaxLifespan": 0,
    "accessCodeLifespan": 60,
    "accessCodeLifespanUserAction": 300,
    "accessCodeLifespanLogin": 1800,
    "actionTokenGeneratedByAdminLifespan": 43200,
    "actionTokenGeneratedByUserLifespan": 300,
    "oauth2DeviceCodeLifespan": 600,
    "oauth2DevicePollingInterval": 5,
    "enabled": true,
    "sslRequired": "external",
    "registrationAllowed": false,
    "registrationEmailAsUsername": false,
    "rememberMe": false,
    "verifyEmail": false,
    "loginWithEmailAllowed": true,
    "duplicateEmailsAllowed": false,
    "resetPasswordAllowed": false,
    "editUsernameAllowed": false,
    "bruteForceProtected": false,
    "permanentLockout": false,
    "maxTemporaryLockouts": 0,
    "bruteForceStrategy": "MULTIPLE",
    "maxFailureWaitSeconds": 900,
    "minimumQuickLoginWaitSeconds": 60,
    "waitIncrementSeconds": 60,
    "quickLoginCheckMilliSeconds": 1000,
    "maxDeltaTimeSeconds": 43200,
    "failureFactor": 30,
    "roles": {
        "realm": [
            {
                "id": "dacb4c5d-8646-4222-b654-afaff2a9b10d",
                "name": "offline_access",
                "description": "${role_offline-access}",
                "composite": false,
                "clientRole": false,
                "containerId": "e96cb526-bba2-42b9-b236-bc5d0b2a3900",
                "attributes": {}
            },
            {
                "id": "7cb41aeb-5d32-4b49-b68c-e0f0b5fc3a66",
                "name": "admin",
                "description": "Verwaltet sein Heimnetz.",
                "composite": false,
                "clientRole": false,
                "containerId": "e96cb526-bba2-42b9-b236-bc5d0b2a3900",
                "attributes": {}
            },
            {
                "id": "2c18d99c-2ffd-4afe-98a6-2a0398df6c2f",
                "name": "uma_authorization",
                "description": "${role_uma_authorization}",
                "composite": false,
                "clientRole": false,
                "containerId": "e96cb526-bba2-42b9-b236-bc5d0b2a3900",
                "attributes": {}
            },
            {
                "id": "4f59861c-c3e7-4648-a018-89d42b903104",
                "name": "default-roles-nethera",
                "description": "${role_default-roles}",
                "composite": true,
                "composites": {
                    "realm": [
                        "offline_access",
                        "uma_authorization"
                    ],
                    "client": {
                        "account": [
                            "view-profile",
                            "manage-account"
                        ]
                    }
                },
                "clientRole": false,
                "containerId": "e96cb526-bba2-42b9-b236-bc5d0b2a3900",
                "attributes": {}
            }
        ],
        "client": {
            "realm-management": [
                {
                    "id": "84078d7c-3802-4e0d-a500-9d1be8f24226",
                    "name": "impersonation",
                    "description": "${role_impersonation}",
                    "composite": false,
                    "clientRole": true,
                    "containerId": "bb32a876-3616-4d46-881b-5e2858483d06",
                    "attributes": {}
                },
                {
                    "id": "3eb59ba3-fa4c-4bea-8b69-9d18d42c6ba4",
                    "name": "manage-realm",
                    "description": "${role_manage-realm}",
                    "composite": false,
                    "clientRole": true,
                    "containerId": "bb32a876-3616-4d46-881b-5e2858483d06",
                    "attributes": {}
                },
                {
                    "id": "1a1e52cc-9c8c-4f68-b930-60a45027c6a8",
                    "name": "query-users",
                    "description": "${role_query-users}",
                    "composite": false,
                    "clientRole": true,
                    "containerId": "bb32a876-3616-4d46-881b-5e2858483d06",
                    "attributes": {}
                },
                {
                    "id": "23fc5f1a-b846-415f-b671-864b8248229e",
                    "name": "view-realm",
                    "description": "${role_view-realm}",
                    "composite": false,
                    "clientRole": true,
                    "containerId": "bb32a876-3616-4d46-881b-5e2858483d06",
                    "attributes": {}
                },
                {
                    "id": "38aadbd9-cef9-4de6-b5a0-c567230142ff",
                    "name": "view-events",
                    "description": "${role_view-events}",
                    "composite": false,
                    "clientRole": true,
                    "containerId": "bb32a876-3616-4d46-881b-5e2858483d06",
                    "attributes": {}
                },
                {
                    "id": "d368face-c88c-42d3-aafa-58a5bf57e614",
                    "name": "manage-authorization",
                    "description": "${role_manage-authorization}",
                    "composite": false,
                    "clientRole": true,
                    "containerId": "bb32a876-3616-4d46-881b-5e2858483d06",
                    "attributes": {}
                },
                {
                    "id": "5b809832-ef22-4aaa-a4af-6e91840ddb9a",
                    "name": "view-identity-providers",
                    "description": "${role_view-identity-providers}",
                    "composite": false,
                    "clientRole": true,
                    "containerId": "bb32a876-3616-4d46-881b-5e2858483d06",
                    "attributes": {}
                },
                {
                    "id": "b5d23b2b-bd0e-43c4-9588-5456e18c4d4b",
                    "name": "manage-clients",
                    "description": "${role_manage-clients}",
                    "composite": false,
                    "clientRole": true,
                    "containerId": "bb32a876-3616-4d46-881b-5e2858483d06",
                    "attributes": {}
                },
                {
                    "id": "0b425da4-5ac6-4e82-a7d7-748749b25634",
                    "name": "query-clients",
                    "description": "${role_query-clients}",
                    "composite": false,
                    "clientRole": true,
                    "containerId": "bb32a876-3616-4d46-881b-5e2858483d06",
                    "attributes": {}
                },
                {
                    "id": "3ab98de0-ddcd-4a9b-89ad-b667f5bc05b5",
                    "name": "query-realms",
                    "description": "${role_query-realms}",
                    "composite": false,
                    "clientRole": true,
                    "containerId": "bb32a876-3616-4d46-881b-5e2858483d06",
                    "attributes": {}
                },
                {
                    "id": "ceca356d-a7a7-4aca-a201-760527ca925c",
                    "name": "manage-events",
                    "description": "${role_manage-events}",
                    "composite": false,
                    "clientRole": true,
                    "containerId": "bb32a876-3616-4d46-881b-5e2858483d06",
                    "attributes": {}
                },
                {
                    "id": "9786cd15-ce70-4737-90dc-a86d28446d9c",
                    "name": "view-users",
                    "description": "${role_view-users}",
                    "composite": true,
                    "composites": {
                        "client": {
                            "realm-management": [
                                "query-users",
                                "query-groups"
                            ]
                        }
                    },
                    "clientRole": true,
                    "containerId": "bb32a876-3616-4d46-881b-5e2858483d06",
                    "attributes": {}
                },
                {
                    "id": "3df6853c-52d3-4f0b-8f31-56a0d71438e5",
                    "name": "manage-users",
                    "description": "${role_manage-users}",
                    "composite": false,
                    "clientRole": true,
                    "containerId": "bb32a876-3616-4d46-881b-5e2858483d06",
                    "attributes": {}
                },
                {
                    "id": "163a5691-1450-41be-bead-a2f0c6c6fc9a",
                    "name": "view-authorization",
                    "description": "${role_view-authorization}",
                    "composite": false,
                    "clientRole": true,
                    "containerId": "bb32a876-3616-4d46-881b-5e2858483d06",
                    "attributes": {}
                },
                {
                    "id": "ec5ceda5-8607-4b9b-96c5-70e14bff8964",
                    "name": "create-client",
                    "description": "${role_create-client}",
                    "composite": false,
                    "clientRole": true,
                    "containerId": "bb32a876-3616-4d46-881b-5e2858483d06",
                    "attributes": {}
                },
                {
                    "id": "369c1994-d832-4a66-8fcb-dd97cfd18d6d",
                    "name": "manage-identity-providers",
                    "description": "${role_manage-identity-providers}",
                    "composite": false,
                    "clientRole": true,
                    "containerId": "bb32a876-3616-4d46-881b-5e2858483d06",
                    "attributes": {}
                },
                {
                    "id": "c4974254-bcee-4b6a-863c-5c3879c88af0",
                    "name": "query-groups",
                    "description": "${role_query-groups}",
                    "composite": false,
                    "clientRole": true,
                    "containerId": "bb32a876-3616-4d46-881b-5e2858483d06",
                    "attributes": {}
                },
                {
                    "id": "3de204ac-c02c-4caf-86e5-7559a966f309",
                    "name": "realm-admin",
                    "description": "${role_realm-admin}",
                    "composite": true,
                    "composites": {
                        "client": {
                            "realm-management": [
                                "manage-realm",
                                "impersonation",
                                "view-realm",
                                "query-users",
                                "view-events",
                                "manage-authorization",
                                "view-identity-providers",
                                "manage-clients",
                                "query-clients",
                                "query-realms",
                                "view-users",
                                "manage-events",
                                "view-authorization",
                                "manage-users",
                                "create-client",
                                "manage-identity-providers",
                                "query-groups",
                                "view-clients"
                            ]
                        }
                    },
                    "clientRole": true,
                    "containerId": "bb32a876-3616-4d46-881b-5e2858483d06",
                    "attributes": {}
                },
                {
                    "id": "c0ed0c09-13d2-4195-abcd-2dfc8749a96d",
                    "name": "view-clients",
                    "description": "${role_view-clients}",
                    "composite": true,
                    "composites": {
                        "client": {
                            "realm-management": [
                                "query-clients"
                            ]
                        }
                    },
                    "clientRole": true,
                    "containerId": "bb32a876-3616-4d46-881b-5e2858483d06",
                    "attributes": {}
                }
            ],
            "security-admin-console": [],
            "nethera-frontend": [],
            "admin-cli": [],
            "account-console": [],
            "broker": [
                {
                    "id": "d698d464-b0c9-4f38-959a-465ae95ec2d8",
                    "name": "read-token",
                    "description": "${role_read-token}",
                    "composite": false,
                    "clientRole": true,
                    "containerId": "f505ced9-ae17-4501-9c83-dd7dbb4125d3",
                    "attributes": {}
                }
            ],
            "account": [
                {
                    "id": "109f0c12-994f-4fad-abc6-5df9782a65fd",
                    "name": "manage-account-links",
                    "description": "${role_manage-account-links}",
                    "composite": false,
                    "clientRole": true,
                    "containerId": "0a09b4d2-0a4a-444d-9c5c-fd3ed62baa00",
                    "attributes": {}
                },
                {
                    "id": "02941a46-bd71-47cc-92b3-7c750c519727",
                    "name": "view-consent",
                    "description": "${role_view-consent}",
                    "composite": false,
                    "clientRole": true,
                    "containerId": "0a09b4d2-0a4a-444d-9c5c-fd3ed62baa00",
                    "attributes": {}
                },
                {
                    "id": "e8280c16-5fe1-44b6-88e7-accd4b695649",
                    "name": "manage-account",
                    "description": "${role_manage-account}",
                    "composite": true,
                    "composites": {
                        "client": {
                            "account": [
                                "manage-account-links"
                            ]
                        }
                    },
                    "clientRole": true,
                    "containerId": "0a09b4d2-0a4a-444d-9c5c-fd3ed62baa00",
                    "attributes": {}
                },
                {
                    "id": "a020a7b3-f552-4e6f-a060-f931d2cf8d78",
                    "name": "view-applications",
                    "description": "${role_view-applications}",
                    "composite": false,
                    "clientRole": true,
                    "containerId": "0a09b4d2-0a4a-444d-9c5c-fd3ed62baa00",
                    "attributes": {}
                },
                {
                    "id": "4fb345bf-5310-4df6-b343-8969b914b82d",
                    "name": "view-profile",
                    "description": "${role_view-profile}",
                    "composite": false,
                    "clientRole": true,
                    "containerId": "0a09b4d2-0a4a-444d-9c5c-fd3ed62baa00",
                    "attributes": {}
                },
                {
                    "id": "6a4d108b-eb7b-45f8-9a5e-b3d6e76971f4",
                    "name": "manage-consent",
                    "description": "${role_manage-consent}",
                    "composite": true,
                    "composites": {
                        "client": {
                            "account": [
                                "view-consent"
                            ]
                        }
                    },
                    "clientRole": true,
                    "containerId": "0a09b4d2-0a4a-444d-9c5c-fd3ed62baa00",
                    "attributes": {}
                },
                {
                    "id": "88c6640c-cd03-41a3-adfc-8171688f0b9b",
                    "name": "view-groups",
                    "description": "${role_view-groups}",
                    "composite": false,
                    "clientRole": true,
                    "containerId": "0a09b4d2-0a4a-444d-9c5c-fd3ed62baa00",
                    "attributes": {}
                },
                {
                    "id": "9421c470-de06-42ae-b814-c8b75695baf4",
                    "name": "delete-account",
                    "description": "${role_delete-account}",
                    "composite": false,
                    "clientRole": true,
                    "containerId": "0a09b4d2-0a4a-444d-9c5c-fd3ed62baa00",
                    "attributes": {}
                }
            ],
            "frontend": []
        }
    },
    "groups": [],
    "defaultRole": {
        "id": "4f59861c-c3e7-4648-a018-89d42b903104",
        "name": "default-roles-nethera",
        "description": "${role_default-roles}",
        "composite": true,
        "clientRole": false,
        "containerId": "e96cb526-bba2-42b9-b236-bc5d0b2a3900"
    },
    "requiredCredentials": [
        "password"
    ],
    "otpPolicyType": "totp",
    "otpPolicyAlgorithm": "HmacSHA1",
    "otpPolicyInitialCounter": 0,
    "otpPolicyDigits": 6,
    "otpPolicyLookAheadWindow": 1,
    "otpPolicyPeriod": 30,
    "otpPolicyCodeReusable": false,
    "otpSupportedApplications": [
        "totpAppFreeOTPName",
        "totpAppGoogleName",
        "totpAppMicrosoftAuthenticatorName"
    ],
    "localizationTexts": {},
    "webAuthnPolicyRpEntityName": "keycloak",
    "webAuthnPolicySignatureAlgorithms": [
        "ES256",
        "RS256"
    ],
    "webAuthnPolicyRpId": "",
    "webAuthnPolicyAttestationConveyancePreference": "not specified",
    "webAuthnPolicyAuthenticatorAttachment": "not specified",
    "webAuthnPolicyRequireResidentKey": "not specified",
    "webAuthnPolicyUserVerificationRequirement": "not specified",
    "webAuthnPolicyCreateTimeout": 0,
    "webAuthnPolicyAvoidSameAuthenticatorRegister": false,
    "webAuthnPolicyAcceptableAaguids": [],
    "webAuthnPolicyExtraOrigins": [],
    "webAuthnPolicyPasswordlessRpEntityName": "keycloak",
    "webAuthnPolicyPasswordlessSignatureAlgorithms": [
        "ES256",
        "RS256"
    ],
    "webAuthnPolicyPasswordlessRpId": "",
    "webAuthnPolicyPasswordlessAttestationConveyancePreference": "not specified",
    "webAuthnPolicyPasswordlessAuthenticatorAttachment": "not specified",
    "webAuthnPolicyPasswordlessRequireResidentKey": "not specified",
    "webAuthnPolicyPasswordlessUserVerificationRequirement": "not specified",
    "webAuthnPolicyPasswordlessCreateTimeout": 0,
    "webAuthnPolicyPasswordlessAvoidSameAuthenticatorRegister": false,
    "webAuthnPolicyPasswordlessAcceptableAaguids": [],
    "webAuthnPolicyPasswordlessExtraOrigins": [],
    "scopeMappings": [
        {
            "clientScope": "offline_access",
            "roles": [
                "offline_access"
            ]
        }
    ],
    "clientScopeMappings": {
        "account": [
            {
                "client": "account-console",
                "roles": [
                    "manage-account",
                    "view-groups"
                ]
            }
        ]
    },
    "clients": [
        {
            "id": "0a09b4d2-0a4a-444d-9c5c-fd3ed62baa00",
            "clientId": "account",
            "name": "${client_account}",
            "rootUrl": "${authBaseUrl}",
            "baseUrl": "/realms/nethera/account/",
            "surrogateAuthRequired": false,
            "enabled": true,
            "alwaysDisplayInConsole": false,
            "clientAuthenticatorType": "client-secret",
            "redirectUris": [
                "/realms/nethera/account/*"
            ],
            "webOrigins": [],
            "notBefore": 0,
            "bearerOnly": false,
            "consentRequired": false,
            "standardFlowEnabled": true,
            "implicitFlowEnabled": false,
            "directAccessGrantsEnabled": false,
            "serviceAccountsEnabled": false,
            "publicClient": true,
            "frontchannelLogout": false,
            "protocol": "openid-connect",
            "attributes": {
                "realm_client": "false",
                "post.logout.redirect.uris": "+"
            },
            "authenticationFlowBindingOverrides": {},
            "fullScopeAllowed": false,
            "nodeReRegistrationTimeout": 0,
            "defaultClientScopes": [
                "web-origins",
                "acr",
                "profile",
                "roles",
                "basic",
                "email"
            ],
            "optionalClientScopes": [
                "address",
                "phone",
                "organization",
                "offline_access",
                "microprofile-jwt"
            ]
        },
        {
            "id": "431f62da-2a2c-4852-a16c-85783b4b980c",
            "clientId": "account-console",
            "name": "${client_account-console}",
            "rootUrl": "${authBaseUrl}",
            "baseUrl": "/realms/nethera/account/",
            "surrogateAuthRequired": false,
            "enabled": true,
            "alwaysDisplayInConsole": false,
            "clientAuthenticatorType": "client-secret",
            "redirectUris": [
                "/realms/nethera/account/*"
            ],
            "webOrigins": [],
            "notBefore": 0,
            "bearerOnly": false,
            "consentRequired": false,
            "standardFlowEnabled": true,
            "implicitFlowEnabled": false,
            "directAccessGrantsEnabled": false,
            "serviceAccountsEnabled": false,
            "publicClient": true,
            "frontchannelLogout": false,
            "protocol": "openid-connect",
            "attributes": {
                "realm_client": "false",
                "post.logout.redirect.uris": "+",
                "pkce.code.challenge.method": "S256"
            },
            "authenticationFlowBindingOverrides": {},
            "fullScopeAllowed": false,
            "nodeReRegistrationTimeout": 0,
            "protocolMappers": [
                {
                    "id": "f34ab23a-cfe4-462c-a107-b8f8d6a25cef",
                    "name": "audience resolve",
                    "protocol": "openid-connect",
                    "protocolMapper": "oidc-audience-resolve-mapper",
                    "consentRequired": false,
                    "config": {}
                }
            ],
            "defaultClientScopes": [
                "web-origins",
                "acr",
                "profile",
                "roles",
                "basic",
                "email"
            ],
            "optionalClientScopes": [
                "address",
                "phone",
                "organization",
                "offline_access",
                "microprofile-jwt"
            ]
        },
        {
            "id": "069495a0-11dd-45d6-b61b-1b959d6199f7",
            "clientId": "admin-cli",
            "name": "${client_admin-cli}",
            "surrogateAuthRequired": false,
            "enabled": true,
            "alwaysDisplayInConsole": false,
            "clientAuthenticatorType": "client-secret",
            "redirectUris": [],
            "webOrigins": [],
            "notBefore": 0,
            "bearerOnly": false,
            "consentRequired": false,
            "standardFlowEnabled": false,
            "implicitFlowEnabled": false,
            "directAccessGrantsEnabled": true,
            "serviceAccountsEnabled": false,
            "publicClient": true,
            "frontchannelLogout": false,
            "protocol": "openid-connect",
            "attributes": {
                "realm_client": "false",
                "client.use.lightweight.access.token.enabled": "true"
            },
            "authenticationFlowBindingOverrides": {},
            "fullScopeAllowed": true,
            "nodeReRegistrationTimeout": 0,
            "defaultClientScopes": [
                "web-origins",
                "acr",
                "profile",
                "roles",
                "basic",
                "email"
            ],
            "optionalClientScopes": [
                "address",
                "phone",
                "organization",
                "offline_access",
                "microprofile-jwt"
            ]
        },
        {
            "id": "f505ced9-ae17-4501-9c83-dd7dbb4125d3",
            "clientId": "broker",
            "name": "${client_broker}",
            "surrogateAuthRequired": false,
            "enabled": true,
            "alwaysDisplayInConsole": false,
            "clientAuthenticatorType": "client-secret",
            "redirectUris": [],
            "webOrigins": [],
            "notBefore": 0,
            "bearerOnly": true,
            "consentRequired": false,
            "standardFlowEnabled": true,
            "implicitFlowEnabled": false,
            "directAccessGrantsEnabled": false,
            "serviceAccountsEnabled": false,
            "publicClient": false,
            "frontchannelLogout": false,
            "protocol": "openid-connect",
            "attributes": {
                "realm_client": "true"
            },
            "authenticationFlowBindingOverrides": {},
            "fullScopeAllowed": false,
            "nodeReRegistrationTimeout": 0,
            "defaultClientScopes": [
                "web-origins",
                "acr",
                "profile",
                "roles",
                "basic",
                "email"
            ],
            "optionalClientScopes": [
                "address",
                "phone",
                "organization",
                "offline_access",
                "microprofile-jwt"
            ]
        },
        {
            "id": "cc82938a-9d3c-4e87-bcf6-7ba205cc3669",
            "clientId": "frontend",
            "name": "frontend",
            "description": "",
            "rootUrl": "",
            "adminUrl": "",
            "baseUrl": "",
            "surrogateAuthRequired": false,
            "enabled": true,
            "alwaysDisplayInConsole": false,
            "clientAuthenticatorType": "client-secret",
            "redirectUris": [
                "*"
            ],
            "webOrigins": [
                "*"
            ],
            "notBefore": 0,
            "bearerOnly": false,
            "consentRequired": false,
            "standardFlowEnabled": true,
            "implicitFlowEnabled": false,
            "directAccessGrantsEnabled": true,
            "serviceAccountsEnabled": false,
            "publicClient": true,
            "frontchannelLogout": true,
            "protocol": "openid-connect",
            "attributes": {
                "realm_client": "false",
                "oidc.ciba.grant.enabled": "false",
                "backchannel.logout.session.required": "true",
                "standard.token.exchange.enabled": "false",
                "frontchannel.logout.session.required": "true",
                "post.logout.redirect.uris": "*",
                "display.on.consent.screen": "false",
                "oauth2.device.authorization.grant.enabled": "false",
                "backchannel.logout.revoke.offline.tokens": "false"
            },
            "authenticationFlowBindingOverrides": {},
            "fullScopeAllowed": true,
            "nodeReRegistrationTimeout": -1,
            "defaultClientScopes": [
                "web-origins",
                "acr",
                "profile",
                "roles",
                "basic",
                "email"
            ],
            "optionalClientScopes": [
                "address",
                "phone",
                "organization",
                "offline_access",
                "microprofile-jwt"
            ]
        },
        {
            "id": "f49c3039-d884-4ea9-9d80-37408203a282",
            "clientId": "nethera-frontend",
            "surrogateAuthRequired": false,
            "enabled": true,
            "alwaysDisplayInConsole": false,
            "clientAuthenticatorType": "client-secret",
            "redirectUris": [],
            "webOrigins": [],
            "notBefore": 0,
            "bearerOnly": false,
            "consentRequired": false,
            "standardFlowEnabled": false,
            "implicitFlowEnabled": false,
            "directAccessGrantsEnabled": true,
            "serviceAccountsEnabled": false,
            "publicClient": true,
            "frontchannelLogout": false,
            "protocol": "openid-connect",
            "attributes": {
                "realm_client": "false"
            },
            "authenticationFlowBindingOverrides": {},
            "fullScopeAllowed": true,
            "nodeReRegistrationTimeout": -1,
            "defaultClientScopes": [
                "web-origins",
                "acr",
                "profile",
                "roles",
                "basic",
                "email"
            ],
            "optionalClientScopes": [
                "address",
                "phone",
                "organization",
                "offline_access",
                "microprofile-jwt"
            ]
        },
        {
            "id": "bb32a876-3616-4d46-881b-5e2858483d06",
            "clientId": "realm-management",
            "name": "${client_realm-management}",
            "surrogateAuthRequired": false,
            "enabled": true,
            "alwaysDisplayInConsole": false,
            "clientAuthenticatorType": "client-secret",
            "redirectUris": [],
            "webOrigins": [],
            "notBefore": 0,
            "bearerOnly": true,
            "consentRequired": false,
            "standardFlowEnabled": true,
            "implicitFlowEnabled": false,
            "directAccessGrantsEnabled": false,
            "serviceAccountsEnabled": false,
            "publicClient": false,
            "frontchannelLogout": false,
            "protocol": "openid-connect",
            "attributes": {
                "realm_client": "true"
            },
            "authenticationFlowBindingOverrides": {},
            "fullScopeAllowed": false,
            "nodeReRegistrationTimeout": 0,
            "defaultClientScopes": [
                "web-origins",
                "acr",
                "profile",
                "roles",
                "basic",
                "email"
            ],
            "optionalClientScopes": [
                "address",
                "phone",
                "organization",
                "offline_access",
                "microprofile-jwt"
            ]
        },
        {
            "id": "20e2ee1e-aa08-429f-96ec-bf7950ef6f36",
            "clientId": "security-admin-console",
            "name": "${client_security-admin-console}",
            "rootUrl": "${authAdminUrl}",
            "baseUrl": "/admin/nethera/console/",
            "surrogateAuthRequired": false,
            "enabled": true,
            "alwaysDisplayInConsole": false,
            "clientAuthenticatorType": "client-secret",
            "redirectUris": [
                "/admin/nethera/console/*"
            ],
            "webOrigins": [
                "+"
            ],
            "notBefore": 0,
            "bearerOnly": false,
            "consentRequired": false,
            "standardFlowEnabled": true,
            "implicitFlowEnabled": false,
            "directAccessGrantsEnabled": false,
            "serviceAccountsEnabled": false,
            "publicClient": true,
            "frontchannelLogout": false,
            "protocol": "openid-connect",
            "attributes": {
                "realm_client": "false",
                "client.use.lightweight.access.token.enabled": "true",
                "post.logout.redirect.uris": "+",
                "pkce.code.challenge.method": "S256"
            },
            "authenticationFlowBindingOverrides": {},
            "fullScopeAllowed": true,
            "nodeReRegistrationTimeout": 0,
            "protocolMappers": [
                {
                    "id": "976ef245-b4e6-4d44-aa9a-3587d7e74b32",
                    "name": "locale",
                    "protocol": "openid-connect",
                    "protocolMapper": "oidc-usermodel-attribute-mapper",
                    "consentRequired": false,
                    "config": {
                        "introspection.token.claim": "true",
                        "userinfo.token.claim": "true",
                        "user.attribute": "locale",
                        "id.token.claim": "true",
                        "access.token.claim": "true",
                        "claim.name": "locale",
                        "jsonType.label": "String"
                    }
                }
            ],
            "defaultClientScopes": [
                "web-origins",
                "acr",
                "profile",
                "roles",
                "basic",
                "email"
            ],
            "optionalClientScopes": [
                "address",
                "phone",
                "organization",
                "offline_access",
                "microprofile-jwt"
            ]
        }
    ],
    "clientScopes": [
        {
            "id": "7c760042-83c1-417e-ab0d-3a5b304f199d",
            "name": "phone",
            "description": "OpenID Connect built-in scope: phone",
            "protocol": "openid-connect",
            "attributes": {
                "include.in.token.scope": "true",
                "consent.screen.text": "${phoneScopeConsentText}",
                "display.on.consent.screen": "true"
            },
            "protocolMappers": [
                {
                    "id": "f39b5ea0-eca2-4474-9965-4eaa1f2f91d2",
                    "name": "phone number verified",
                    "protocol": "openid-connect",
                    "protocolMapper": "oidc-usermodel-attribute-mapper",
                    "consentRequired": false,
                    "config": {
                        "introspection.token.claim": "true",
                        "userinfo.token.claim": "true",
                        "user.attribute": "phoneNumberVerified",
                        "id.token.claim": "true",
                        "access.token.claim": "true",
                        "claim.name": "phone_number_verified",
                        "jsonType.label": "boolean"
                    }
                },
                {
                    "id": "19559f5d-4ccb-4007-bf90-df8c30926650",
                    "name": "phone number",
                    "protocol": "openid-connect",
                    "protocolMapper": "oidc-usermodel-attribute-mapper",
                    "consentRequired": false,
                    "config": {
                        "introspection.token.claim": "true",
                        "userinfo.token.claim": "true",
                        "user.attribute": "phoneNumber",
                        "id.token.claim": "true",
                        "access.token.claim": "true",
                        "claim.name": "phone_number",
                        "jsonType.label": "String"
                    }
                }
            ]
        },
        {
            "id": "7fb8a03e-5c6f-4851-b7a0-1cb95fe7388a",
            "name": "service_account",
            "description": "Specific scope for a client enabled for service accounts",
            "protocol": "openid-connect",
            "attributes": {
                "include.in.token.scope": "false",
                "display.on.consent.screen": "false"
            },
            "protocolMappers": [
                {
                    "id": "7c953959-e211-4a6a-ac67-e8333fb599c9",
                    "name": "Client IP Address",
                    "protocol": "openid-connect",
                    "protocolMapper": "oidc-usersessionmodel-note-mapper",
                    "consentRequired": false,
                    "config": {
                        "user.session.note": "clientAddress",
                        "id.token.claim": "true",
                        "introspection.token.claim": "true",
                        "access.token.claim": "true",
                        "claim.name": "clientAddress",
                        "jsonType.label": "String"
                    }
                },
                {
                    "id": "6f08b9d1-c012-4029-92de-3304869f8f8e",
                    "name": "Client Host",
                    "protocol": "openid-connect",
                    "protocolMapper": "oidc-usersessionmodel-note-mapper",
                    "consentRequired": false,
                    "config": {
                        "user.session.note": "clientHost",
                        "id.token.claim": "true",
                        "introspection.token.claim": "true",
                        "access.token.claim": "true",
                        "claim.name": "clientHost",
                        "jsonType.label": "String"
                    }
                },
                {
                    "id": "b94570e3-39f8-4f41-b594-19b6d5d2c5d1",
                    "name": "Client ID",
                    "protocol": "openid-connect",
                    "protocolMapper": "oidc-usersessionmodel-note-mapper",
                    "consentRequired": false,
                    "config": {
                        "user.session.note": "client_id",
                        "id.token.claim": "true",
                        "introspection.token.claim": "true",
                        "access.token.claim": "true",
                        "claim.name": "client_id",
                        "jsonType.label": "String"
                    }
                }
            ]
        },
        {
            "id": "64b34786-dcb6-454b-8ebe-09e9e1e6ecdd",
            "name": "organization",
            "description": "Additional claims about the organization a subject belongs to",
            "protocol": "openid-connect",
            "attributes": {
                "include.in.token.scope": "true",
                "consent.screen.text": "${organizationScopeConsentText}",
                "display.on.consent.screen": "true"
            },
            "protocolMappers": [
                {
                    "id": "da9118d7-fc9c-41ea-9e39-872da8d5fde1",
                    "name": "organization",
                    "protocol": "openid-connect",
                    "protocolMapper": "oidc-organization-membership-mapper",
                    "consentRequired": false,
                    "config": {
                        "id.token.claim": "true",
                        "introspection.token.claim": "true",
                        "access.token.claim": "true",
                        "claim.name": "organization",
                        "jsonType.label": "String",
                        "multivalued": "true"
                    }
                }
            ]
        },
        {
            "id": "85876eed-9f1f-44a4-b1e9-edd9868e5fe2",
            "name": "basic",
            "description": "OpenID Connect scope for add all basic claims to the token",
            "protocol": "openid-connect",
            "attributes": {
                "include.in.token.scope": "false",
                "display.on.consent.screen": "false"
            },
            "protocolMappers": [
                {
                    "id": "11050463-febe-461f-af30-69f7e7d4083e",
                    "name": "auth_time",
                    "protocol": "openid-connect",
                    "protocolMapper": "oidc-usersessionmodel-note-mapper",
                    "consentRequired": false,
                    "config": {
                        "user.session.note": "AUTH_TIME",
                        "id.token.claim": "true",
                        "introspection.token.claim": "true",
                        "access.token.claim": "true",
                        "claim.name": "auth_time",
                        "jsonType.label": "long"
                    }
                },
                {
                    "id": "409bf354-7220-409f-be95-d7ec8a48ccfe",
                    "name": "sub",
                    "protocol": "openid-connect",
                    "protocolMapper": "oidc-sub-mapper",
                    "consentRequired": false,
                    "config": {
                        "introspection.token.claim": "true",
                        "access.token.claim": "true"
                    }
                }
            ]
        },
        {
            "id": "68e4a442-3e15-4e0f-b21b-91e4a43beacc",
            "name": "address",
            "description": "OpenID Connect built-in scope: address",
            "protocol": "openid-connect",
            "attributes": {
                "include.in.token.scope": "true",
                "consent.screen.text": "${addressScopeConsentText}",
                "display.on.consent.screen": "true"
            },
            "protocolMappers": [
                {
                    "id": "763bca4b-ed66-4389-a92a-ae552e398f85",
                    "name": "address",
                    "protocol": "openid-connect",
                    "protocolMapper": "oidc-address-mapper",
                    "consentRequired": false,
                    "config": {
                        "user.attribute.formatted": "formatted",
                        "user.attribute.country": "country",
                        "introspection.token.claim": "true",
                        "user.attribute.postal_code": "postal_code",
                        "userinfo.token.claim": "true",
                        "user.attribute.street": "street",
                        "id.token.claim": "true",
                        "user.attribute.region": "region",
                        "access.token.claim": "true",
                        "user.attribute.locality": "locality"
                    }
                }
            ]
        },
        {
            "id": "5cba8b54-e24f-428d-8720-d398686c4a6d",
            "name": "profile",
            "description": "OpenID Connect built-in scope: profile",
            "protocol": "openid-connect",
            "attributes": {
                "include.in.token.scope": "true",
                "consent.screen.text": "${profileScopeConsentText}",
                "display.on.consent.screen": "true"
            },
            "protocolMappers": [
                {
                    "id": "66dcdc99-43d6-4826-9d68-1029e10d740d",
                    "name": "gender",
                    "protocol": "openid-connect",
                    "protocolMapper": "oidc-usermodel-attribute-mapper",
                    "consentRequired": false,
                    "config": {
                        "introspection.token.claim": "true",
                        "userinfo.token.claim": "true",
                        "user.attribute": "gender",
                        "id.token.claim": "true",
                        "access.token.claim": "true",
                        "claim.name": "gender",
                        "jsonType.label": "String"
                    }
                },
                {
                    "id": "02ea0217-52dc-4d4d-aac4-c9937250e3d6",
                    "name": "zoneinfo",
                    "protocol": "openid-connect",
                    "protocolMapper": "oidc-usermodel-attribute-mapper",
                    "consentRequired": false,
                    "config": {
                        "introspection.token.claim": "true",
                        "userinfo.token.claim": "true",
                        "user.attribute": "zoneinfo",
                        "id.token.claim": "true",
                        "access.token.claim": "true",
                        "claim.name": "zoneinfo",
                        "jsonType.label": "String"
                    }
                },
                {
                    "id": "16b9b495-7bfd-44a3-aba9-68a54cc11879",
                    "name": "full name",
                    "protocol": "openid-connect",
                    "protocolMapper": "oidc-full-name-mapper",
                    "consentRequired": false,
                    "config": {
                        "id.token.claim": "true",
                        "introspection.token.claim": "true",
                        "access.token.claim": "true",
                        "userinfo.token.claim": "true"
                    }
                },
                {
                    "id": "22bc819c-95e8-4b64-941b-076182990679",
                    "name": "profile",
                    "protocol": "openid-connect",
                    "protocolMapper": "oidc-usermodel-attribute-mapper",
                    "consentRequired": false,
                    "config": {
                        "introspection.token.claim": "true",
                        "userinfo.token.claim": "true",
                        "user.attribute": "profile",
                        "id.token.claim": "true",
                        "access.token.claim": "true",
                        "claim.name": "profile",
                        "jsonType.label": "String"
                    }
                },
                {
                    "id": "bb8d18d2-5242-4607-a523-92a0b373eb8f",
                    "name": "website",
                    "protocol": "openid-connect",
                    "protocolMapper": "oidc-usermodel-attribute-mapper",
                    "consentRequired": false,
                    "config": {
                        "introspection.token.claim": "true",
                        "userinfo.token.claim": "true",
                        "user.attribute": "website",
                        "id.token.claim": "true",
                        "access.token.claim": "true",
                        "claim.name": "website",
                        "jsonType.label": "String"
                    }
                },
                {
                    "id": "83394be1-dc30-40cb-ac90-a343a6d3115d",
                    "name": "locale",
                    "protocol": "openid-connect",
                    "protocolMapper": "oidc-usermodel-attribute-mapper",
                    "consentRequired": false,
                    "config": {
                        "introspection.token.claim": "true",
                        "userinfo.token.claim": "true",
                        "user.attribute": "locale",
                        "id.token.claim": "true",
                        "access.token.claim": "true",
                        "claim.name": "locale",
                        "jsonType.label": "String"
                    }
                },
                {
                    "id": "4a7dedf0-98d6-48b4-9c58-6a2351b77225",
                    "name": "picture",
                    "protocol": "openid-connect",
                    "protocolMapper": "oidc-usermodel-attribute-mapper",
                    "consentRequired": false,
                    "config": {
                        "introspection.token.claim": "true",
                        "userinfo.token.claim": "true",
                        "user.attribute": "picture",
                        "id.token.claim": "true",
                        "access.token.claim": "true",
                        "claim.name": "picture",
                        "jsonType.label": "String"
                    }
                },
                {
                    "id": "85dbc5d4-4d35-4b45-8db7-b5afcac9206d",
                    "name": "birthdate",
                    "protocol": "openid-connect",
                    "protocolMapper": "oidc-usermodel-attribute-mapper",
                    "consentRequired": false,
                    "config": {
                        "introspection.token.claim": "true",
                        "userinfo.token.claim": "true",
                        "user.attribute": "birthdate",
                        "id.token.claim": "true",
                        "access.token.claim": "true",
                        "claim.name": "birthdate",
                        "jsonType.label": "String"
                    }
                },
                {
                    "id": "1997adf8-7104-40af-b763-c34dc4b68eb1",
                    "name": "nickname",
                    "protocol": "openid-connect",
                    "protocolMapper": "oidc-usermodel-attribute-mapper",
                    "consentRequired": false,
                    "config": {
                        "introspection.token.claim": "true",
                        "userinfo.token.claim": "true",
                        "user.attribute": "nickname",
                        "id.token.claim": "true",
                        "access.token.claim": "true",
                        "claim.name": "nickname",
                        "jsonType.label": "String"
                    }
                },
                {
                    "id": "6ecd8978-55dd-41c3-a763-34eacf9225ca",
                    "name": "updated at",
                    "protocol": "openid-connect",
                    "protocolMapper": "oidc-usermodel-attribute-mapper",
                    "consentRequired": false,
                    "config": {
                        "introspection.token.claim": "true",
                        "userinfo.token.claim": "true",
                        "user.attribute": "updatedAt",
                        "id.token.claim": "true",
                        "access.token.claim": "true",
                        "claim.name": "updated_at",
                        "jsonType.label": "long"
                    }
                },
                {
                    "id": "e0407226-699a-4cd3-a388-18fcfe350d29",
                    "name": "family name",
                    "protocol": "openid-connect",
                    "protocolMapper": "oidc-usermodel-attribute-mapper",
                    "consentRequired": false,
                    "config": {
                        "introspection.token.claim": "true",
                        "userinfo.token.claim": "true",
                        "user.attribute": "lastName",
                        "id.token.claim": "true",
                        "access.token.claim": "true",
                        "claim.name": "family_name",
                        "jsonType.label": "String"
                    }
                },
                {
                    "id": "af92b66b-9ca9-4ebd-add1-d677181bf837",
                    "name": "given name",
                    "protocol": "openid-connect",
                    "protocolMapper": "oidc-usermodel-attribute-mapper",
                    "consentRequired": false,
                    "config": {
                        "introspection.token.claim": "true",
                        "userinfo.token.claim": "true",
                        "user.attribute": "firstName",
                        "id.token.claim": "true",
                        "access.token.claim": "true",
                        "claim.name": "given_name",
                        "jsonType.label": "String"
                    }
                },
                {
                    "id": "103c9612-462c-43c3-a3d1-ca5161986dc6",
                    "name": "username",
                    "protocol": "openid-connect",
                    "protocolMapper": "oidc-usermodel-attribute-mapper",
                    "consentRequired": false,
                    "config": {
                        "introspection.token.claim": "true",
                        "userinfo.token.claim": "true",
                        "user.attribute": "username",
                        "id.token.claim": "true",
                        "access.token.claim": "true",
                        "claim.name": "preferred_username",
                        "jsonType.label": "String"
                    }
                },
                {
                    "id": "303e7b75-bab6-4652-8e04-60f42a459002",
                    "name": "middle name",
                    "protocol": "openid-connect",
                    "protocolMapper": "oidc-usermodel-attribute-mapper",
                    "consentRequired": false,
                    "config": {
                        "introspection.token.claim": "true",
                        "userinfo.token.claim": "true",
                        "user.attribute": "middleName",
                        "id.token.claim": "true",
                        "access.token.claim": "true",
                        "claim.name": "middle_name",
                        "jsonType.label": "String"
                    }
                }
            ]
        },
        {
            "id": "76ade760-d9b2-4434-804b-e1023acc2125",
            "name": "offline_access",
            "description": "OpenID Connect built-in scope: offline_access",
            "protocol": "openid-connect",
            "attributes": {
                "consent.screen.text": "${offlineAccessScopeConsentText}",
                "display.on.consent.screen": "true"
            }
        },
        {
            "id": "9a5f66d1-f805-4afc-897b-0c71ba1c5da6",
            "name": "roles",
            "description": "OpenID Connect scope for add user roles to the access token",
            "protocol": "openid-connect",
            "attributes": {
                "include.in.token.scope": "false",
                "consent.screen.text": "${rolesScopeConsentText}",
                "display.on.consent.screen": "true"
            },
            "protocolMappers": [
                {
                    "id": "48eb00e6-cb6f-48a5-96c7-54adb552e825",
                    "name": "realm roles",
                    "protocol": "openid-connect",
                    "protocolMapper": "oidc-usermodel-realm-role-mapper",
                    "consentRequired": false,
                    "config": {
                        "user.attribute": "foo",
                        "introspection.token.claim": "true",
                        "access.token.claim": "true",
                        "claim.name": "realm_access.roles",
                        "jsonType.label": "String",
                        "multivalued": "true"
                    }
                },
                {
                    "id": "20f9183f-42cb-4772-a807-b563bea5366f",
                    "name": "audience resolve",
                    "protocol": "openid-connect",
                    "protocolMapper": "oidc-audience-resolve-mapper",
                    "consentRequired": false,
                    "config": {
                        "introspection.token.claim": "true",
                        "access.token.claim": "true"
                    }
                },
                {
                    "id": "1546fd9f-98e0-4b24-9e27-637bf5fb34a5",
                    "name": "client roles",
                    "protocol": "openid-connect",
                    "protocolMapper": "oidc-usermodel-client-role-mapper",
                    "consentRequired": false,
                    "config": {
                        "user.attribute": "foo",
                        "introspection.token.claim": "true",
                        "access.token.claim": "true",
                        "claim.name": "resource_access.${client_id}.roles",
                        "jsonType.label": "String",
                        "multivalued": "true"
                    }
                }
            ]
        },
        {
            "id": "6e66408e-0abe-49b8-9b3d-3c0d903c01bc",
            "name": "acr",
            "description": "OpenID Connect scope for add acr (authentication context class reference) to the token",
            "protocol": "openid-connect",
            "attributes": {
                "include.in.token.scope": "false",
                "display.on.consent.screen": "false"
            },
            "protocolMappers": [
                {
                    "id": "95e9c47b-97a6-4454-871c-31506c0060e6",
                    "name": "acr loa level",
                    "protocol": "openid-connect",
                    "protocolMapper": "oidc-acr-mapper",
                    "consentRequired": false,
                    "config": {
                        "id.token.claim": "true",
                        "introspection.token.claim": "true",
                        "access.token.claim": "true"
                    }
                }
            ]
        },
        {
            "id": "dc99c5c1-0168-45ba-8e6f-36aa38ad1e45",
            "name": "web-origins",
            "description": "OpenID Connect scope for add allowed web origins to the access token",
            "protocol": "openid-connect",
            "attributes": {
                "include.in.token.scope": "false",
                "consent.screen.text": "",
                "display.on.consent.screen": "false"
            },
            "protocolMappers": [
                {
                    "id": "5f049119-8ab1-4490-8af4-aef04e7a9f40",
                    "name": "allowed web origins",
                    "protocol": "openid-connect",
                    "protocolMapper": "oidc-allowed-origins-mapper",
                    "consentRequired": false,
                    "config": {
                        "introspection.token.claim": "true",
                        "access.token.claim": "true"
                    }
                }
            ]
        },
        {
            "id": "e4e8ebbc-b619-48eb-bc90-3e0fb6276da8",
            "name": "microprofile-jwt",
            "description": "Microprofile - JWT built-in scope",
            "protocol": "openid-connect",
            "attributes": {
                "include.in.token.scope": "true",
                "display.on.consent.screen": "false"
            },
            "protocolMappers": [
                {
                    "id": "a319bcc3-a235-4364-ae0a-afd786847b14",
                    "name": "upn",
                    "protocol": "openid-connect",
                    "protocolMapper": "oidc-usermodel-attribute-mapper",
                    "consentRequired": false,
                    "config": {
                        "introspection.token.claim": "true",
                        "userinfo.token.claim": "true",
                        "user.attribute": "username",
                        "id.token.claim": "true",
                        "access.token.claim": "true",
                        "claim.name": "upn",
                        "jsonType.label": "String"
                    }
                },
                {
                    "id": "dbb472f0-2eba-4898-acde-3cab7e0992ea",
                    "name": "groups",
                    "protocol": "openid-connect",
                    "protocolMapper": "oidc-usermodel-realm-role-mapper",
                    "consentRequired": false,
                    "config": {
                        "introspection.token.claim": "true",
                        "multivalued": "true",
                        "user.attribute": "foo",
                        "id.token.claim": "true",
                        "access.token.claim": "true",
                        "claim.name": "groups",
                        "jsonType.label": "String"
                    }
                }
            ]
        },
        {
            "id": "bf3dce65-e9a9-40bf-a7d2-3da27f884192",
            "name": "role_list",
            "description": "SAML role list",
            "protocol": "saml",
            "attributes": {
                "consent.screen.text": "${samlRoleListScopeConsentText}",
                "display.on.consent.screen": "true"
            },
            "protocolMappers": [
                {
                    "id": "789d6161-b469-4288-91bb-2553b0086839",
                    "name": "role list",
                    "protocol": "saml",
                    "protocolMapper": "saml-role-list-mapper",
                    "consentRequired": false,
                    "config": {
                        "single": "false",
                        "attribute.nameformat": "Basic",
                        "attribute.name": "Role"
                    }
                }
            ]
        },
        {
            "id": "02fadef7-1d2d-40bd-80c5-bdea82e8aad2",
            "name": "email",
            "description": "OpenID Connect built-in scope: email",
            "protocol": "openid-connect",
            "attributes": {
                "include.in.token.scope": "true",
                "consent.screen.text": "${emailScopeConsentText}",
                "display.on.consent.screen": "true"
            },
            "protocolMappers": [
                {
                    "id": "67bafa3a-6b3d-400b-baf8-0c07928dff28",
                    "name": "email",
                    "protocol": "openid-connect",
                    "protocolMapper": "oidc-usermodel-attribute-mapper",
                    "consentRequired": false,
                    "config": {
                        "introspection.token.claim": "true",
                        "userinfo.token.claim": "true",
                        "user.attribute": "email",
                        "id.token.claim": "true",
                        "access.token.claim": "true",
                        "claim.name": "email",
                        "jsonType.label": "String"
                    }
                },
                {
                    "id": "a74c148c-e858-4598-a88b-30a47d7123e5",
                    "name": "email verified",
                    "protocol": "openid-connect",
                    "protocolMapper": "oidc-usermodel-property-mapper",
                    "consentRequired": false,
                    "config": {
                        "introspection.token.claim": "true",
                        "userinfo.token.claim": "true",
                        "user.attribute": "emailVerified",
                        "id.token.claim": "true",
                        "access.token.claim": "true",
                        "claim.name": "email_verified",
                        "jsonType.label": "boolean"
                    }
                }
            ]
        },
        {
            "id": "6c022af2-5c90-467c-ad71-709528b8f0b9",
            "name": "saml_organization",
            "description": "Organization Membership",
            "protocol": "saml",
            "attributes": {
                "display.on.consent.screen": "false"
            },
            "protocolMappers": [
                {
                    "id": "83540ade-d048-49a4-9821-0dd8dc7e3b4b",
                    "name": "organization",
                    "protocol": "saml",
                    "protocolMapper": "saml-organization-membership-mapper",
                    "consentRequired": false,
                    "config": {}
                }
            ]
        }
    ],
    "defaultDefaultClientScopes": [
        "role_list",
        "saml_organization",
        "profile",
        "email",
        "roles",
        "web-origins",
        "acr",
        "basic"
    ],
    "defaultOptionalClientScopes": [
        "offline_access",
        "address",
        "phone",
        "microprofile-jwt",
        "organization"
    ],
    "browserSecurityHeaders": {
        "contentSecurityPolicyReportOnly": "",
        "xContentTypeOptions": "nosniff",
        "referrerPolicy": "no-referrer",
        "xRobotsTag": "none",
        "xFrameOptions": "SAMEORIGIN",
        "contentSecurityPolicy": "frame-src 'self'; frame-ancestors 'self'; object-src 'none';",
        "strictTransportSecurity": "max-age=31536000; includeSubDomains"
    },
    "smtpServer": {},
    "eventsEnabled": false,
    "eventsListeners": [
        "jboss-logging"
    ],
    "enabledEventTypes": [],
    "adminEventsEnabled": false,
    "adminEventsDetailsEnabled": false,
    "identityProviders": [],
    "identityProviderMappers": [],
    "components": {
        "org.keycloak.services.clientregistration.policy.ClientRegistrationPolicy": [
            {
                "id": "2f6a53e8-2b56-4ef9-941c-4511f37dd393",
                "name": "Trusted Hosts",
                "providerId": "trusted-hosts",
                "subType": "anonymous",
                "subComponents": {},
                "config": {
                    "host-sending-registration-request-must-match": [
                        "true"
                    ],
                    "client-uris-must-match": [
                        "true"
                    ]
                }
            },
            {
                "id": "566f7f85-5c03-41da-844b-05265d7e0e83",
                "name": "Full Scope Disabled",
                "providerId": "scope",
                "subType": "anonymous",
                "subComponents": {},
                "config": {}
            },
            {
                "id": "4bdea47c-437e-49fc-8dd5-81bb2d2d8a53",
                "name": "Allowed Protocol Mapper Types",
                "providerId": "allowed-protocol-mappers",
                "subType": "anonymous",
                "subComponents": {},
                "config": {
                    "allowed-protocol-mapper-types": [
                        "saml-user-attribute-mapper",
                        "oidc-usermodel-property-mapper",
                        "oidc-usermodel-attribute-mapper",
                        "oidc-address-mapper",
                        "oidc-sha256-pairwise-sub-mapper",
                        "saml-role-list-mapper",
                        "saml-user-property-mapper",
                        "oidc-full-name-mapper"
                    ]
                }
            },
            {
                "id": "36f4e1c0-6ee7-40e2-b325-e13c66272835",
                "name": "Consent Required",
                "providerId": "consent-required",
                "subType": "anonymous",
                "subComponents": {},
                "config": {}
            },
            {
                "id": "4b15ca23-3e55-4171-a2f1-b2b1496e1911",
                "name": "Allowed Client Scopes",
                "providerId": "allowed-client-templates",
                "subType": "anonymous",
                "subComponents": {},
                "config": {
                    "allow-default-scopes": [
                        "true"
                    ]
                }
            },
            {
                "id": "32bb86a8-e000-4340-8462-0309ac3a36fe",
                "name": "Allowed Client Scopes",
                "providerId": "allowed-client-templates",
                "subType": "authenticated",
                "subComponents": {},
                "config": {
                    "allow-default-scopes": [
                        "true"
                    ]
                }
            },
            {
                "id": "d6891592-513b-441c-8e3a-8ca1a4f456fe",
                "name": "Max Clients Limit",
                "providerId": "max-clients",
                "subType": "anonymous",
                "subComponents": {},
                "config": {
                    "max-clients": [
                        "200"
                    ]
                }
            },
            {
                "id": "e261c7ff-26d4-4dac-b69d-dc9dc7ece57a",
                "name": "Allowed Protocol Mapper Types",
                "providerId": "allowed-protocol-mappers",
                "subType": "authenticated",
                "subComponents": {},
                "config": {
                    "allowed-protocol-mapper-types": [
                        "saml-role-list-mapper",
                        "oidc-usermodel-property-mapper",
                        "oidc-full-name-mapper",
                        "saml-user-attribute-mapper",
                        "oidc-sha256-pairwise-sub-mapper",
                        "oidc-usermodel-attribute-mapper",
                        "saml-user-property-mapper",
                        "oidc-address-mapper"
                    ]
                }
            }
        ],
        "org.keycloak.keys.KeyProvider": [
            {
                "id": "34f42110-c8c3-4f71-86a4-91663c216bb9",
                "name": "aes-generated",
                "providerId": "aes-generated",
                "subComponents": {},
                "config": {
                    "priority": [
                        "100"
                    ]
                }
            },
            {
                "id": "b0e4ec15-208b-4c49-9ec4-69b03ddab6fb",
                "name": "hmac-generated-hs512",
                "providerId": "hmac-generated",
                "subComponents": {},
                "config": {
                    "priority": [
                        "100"
                    ],
                    "algorithm": [
                        "HS512"
                    ]
                }
            },
            {
                "id": "a5e3885c-92d6-4def-965e-fd20a98e2448",
                "name": "rsa-generated",
                "providerId": "rsa-generated",
                "subComponents": {},
                "config": {
                    "priority": [
                        "100"
                    ]
                }
            },
            {
                "id": "0d939df3-67f9-44ff-a965-4928f4e12d70",
                "name": "rsa-enc-generated",
                "providerId": "rsa-enc-generated",
                "subComponents": {},
                "config": {
                    "priority": [
                        "100"
                    ],
                    "algorithm": [
                        "RSA-OAEP"
                    ]
                }
            }
        ]
    },
    "internationalizationEnabled": false,
    "supportedLocales": [],
    "authenticationFlows": [
        {
            "id": "7f6e3817-1ba5-4276-adea-7c3e0efbea40",
            "alias": "Account verification options",
            "description": "Method with which to verity the existing account",
            "providerId": "basic-flow",
            "topLevel": false,
            "builtIn": true,
            "authenticationExecutions": [
                {
                    "authenticator": "idp-email-verification",
                    "authenticatorFlow": false,
                    "requirement": "ALTERNATIVE",
                    "priority": 10,
                    "autheticatorFlow": false,
                    "userSetupAllowed": false
                },
                {
                    "authenticatorFlow": true,
                    "requirement": "ALTERNATIVE",
                    "priority": 20,
                    "autheticatorFlow": true,
                    "flowAlias": "Verify Existing Account by Re-authentication",
                    "userSetupAllowed": false
                }
            ]
        },
        {
            "id": "76c6efd5-b35b-44a9-a5ea-89d77a6a1616",
            "alias": "Browser - Conditional OTP",
            "description": "Flow to determine if the OTP is required for the authentication",
            "providerId": "basic-flow",
            "topLevel": false,
            "builtIn": true,
            "authenticationExecutions": [
                {
                    "authenticator": "conditional-user-configured",
                    "authenticatorFlow": false,
                    "requirement": "REQUIRED",
                    "priority": 10,
                    "autheticatorFlow": false,
                    "userSetupAllowed": false
                },
                {
                    "authenticator": "auth-otp-form",
                    "authenticatorFlow": false,
                    "requirement": "REQUIRED",
                    "priority": 20,
                    "autheticatorFlow": false,
                    "userSetupAllowed": false
                }
            ]
        },
        {
            "id": "c25297c2-0981-4103-bcdb-396ca5bf9c2e",
            "alias": "Browser - Conditional Organization",
            "description": "Flow to determine if the organization identity-first login is to be used",
            "providerId": "basic-flow",
            "topLevel": false,
            "builtIn": true,
            "authenticationExecutions": [
                {
                    "authenticator": "conditional-user-configured",
                    "authenticatorFlow": false,
                    "requirement": "REQUIRED",
                    "priority": 10,
                    "autheticatorFlow": false,
                    "userSetupAllowed": false
                },
                {
                    "authenticator": "organization",
                    "authenticatorFlow": false,
                    "requirement": "ALTERNATIVE",
                    "priority": 20,
                    "autheticatorFlow": false,
                    "userSetupAllowed": false
                }
            ]
        },
        {
            "id": "c158b0f7-adb3-4ed9-99fd-3f8a40b9036b",
            "alias": "Direct Grant - Conditional OTP",
            "description": "Flow to determine if the OTP is required for the authentication",
            "providerId": "basic-flow",
            "topLevel": false,
            "builtIn": true,
            "authenticationExecutions": [
                {
                    "authenticator": "conditional-user-configured",
                    "authenticatorFlow": false,
                    "requirement": "REQUIRED",
                    "priority": 10,
                    "autheticatorFlow": false,
                    "userSetupAllowed": false
                },
                {
                    "authenticator": "direct-grant-validate-otp",
                    "authenticatorFlow": false,
                    "requirement": "REQUIRED",
                    "priority": 20,
                    "autheticatorFlow": false,
                    "userSetupAllowed": false
                }
            ]
        },
        {
            "id": "3e27e4f8-3e93-434d-b22f-6d5400340a3e",
            "alias": "First Broker Login - Conditional Organization",
            "description": "Flow to determine if the authenticator that adds organization members is to be used",
            "providerId": "basic-flow",
            "topLevel": false,
            "builtIn": true,
            "authenticationExecutions": [
                {
                    "authenticator": "conditional-user-configured",
                    "authenticatorFlow": false,
                    "requirement": "REQUIRED",
                    "priority": 10,
                    "autheticatorFlow": false,
                    "userSetupAllowed": false
                },
                {
                    "authenticator": "idp-add-organization-member",
                    "authenticatorFlow": false,
                    "requirement": "REQUIRED",
                    "priority": 20,
                    "autheticatorFlow": false,
                    "userSetupAllowed": false
                }
            ]
        },
        {
            "id": "44dcaf85-ae97-4ee5-a265-837e05527b8c",
            "alias": "First broker login - Conditional OTP",
            "description": "Flow to determine if the OTP is required for the authentication",
            "providerId": "basic-flow",
            "topLevel": false,
            "builtIn": true,
            "authenticationExecutions": [
                {
                    "authenticator": "conditional-user-configured",
                    "authenticatorFlow": false,
                    "requirement": "REQUIRED",
                    "priority": 10,
                    "autheticatorFlow": false,
                    "userSetupAllowed": false
                },
                {
                    "authenticator": "auth-otp-form",
                    "authenticatorFlow": false,
                    "requirement": "REQUIRED",
                    "priority": 20,
                    "autheticatorFlow": false,
                    "userSetupAllowed": false
                }
            ]
        },
        {
            "id": "854233aa-6bd4-49c0-95fc-089b97012b17",
            "alias": "Handle Existing Account",
            "description": "Handle what to do if there is existing account with same email/username like authenticated identity provider",
            "providerId": "basic-flow",
            "topLevel": false,
            "builtIn": true,
            "authenticationExecutions": [
                {
                    "authenticator": "idp-confirm-link",
                    "authenticatorFlow": false,
                    "requirement": "REQUIRED",
                    "priority": 10,
                    "autheticatorFlow": false,
                    "userSetupAllowed": false
                },
                {
                    "authenticatorFlow": true,
                    "requirement": "REQUIRED",
                    "priority": 20,
                    "autheticatorFlow": true,
                    "flowAlias": "Account verification options",
                    "userSetupAllowed": false
                }
            ]
        },
        {
            "id": "a24597de-702b-46d9-9995-c2d9221d2bbb",
            "alias": "Organization",
            "providerId": "basic-flow",
            "topLevel": false,
            "builtIn": true,
            "authenticationExecutions": [
                {
                    "authenticatorFlow": true,
                    "requirement": "CONDITIONAL",
                    "priority": 10,
                    "autheticatorFlow": true,
                    "flowAlias": "Browser - Conditional Organization",
                    "userSetupAllowed": false
                }
            ]
        },
        {
            "id": "9a463279-1526-48f4-8b4a-c55b48d849ba",
            "alias": "Reset - Conditional OTP",
            "description": "Flow to determine if the OTP should be reset or not. Set to REQUIRED to force.",
            "providerId": "basic-flow",
            "topLevel": false,
            "builtIn": true,
            "authenticationExecutions": [
                {
                    "authenticator": "conditional-user-configured",
                    "authenticatorFlow": false,
                    "requirement": "REQUIRED",
                    "priority": 10,
                    "autheticatorFlow": false,
                    "userSetupAllowed": false
                },
                {
                    "authenticator": "reset-otp",
                    "authenticatorFlow": false,
                    "requirement": "REQUIRED",
                    "priority": 20,
                    "autheticatorFlow": false,
                    "userSetupAllowed": false
                }
            ]
        },
        {
            "id": "dcb16b37-3e88-4e3e-a6d0-dfe051f4fbd5",
            "alias": "User creation or linking",
            "description": "Flow for the existing/non-existing user alternatives",
            "providerId": "basic-flow",
            "topLevel": false,
            "builtIn": true,
            "authenticationExecutions": [
                {
                    "authenticatorConfig": "create unique user config",
                    "authenticator": "idp-create-user-if-unique",
                    "authenticatorFlow": false,
                    "requirement": "ALTERNATIVE",
                    "priority": 10,
                    "autheticatorFlow": false,
                    "userSetupAllowed": false
                },
                {
                    "authenticatorFlow": true,
                    "requirement": "ALTERNATIVE",
                    "priority": 20,
                    "autheticatorFlow": true,
                    "flowAlias": "Handle Existing Account",
                    "userSetupAllowed": false
                }
            ]
        },
        {
            "id": "21c7c109-8d60-4b86-93e1-6e9db54beb44",
            "alias": "Verify Existing Account by Re-authentication",
            "description": "Reauthentication of existing account",
            "providerId": "basic-flow",
            "topLevel": false,
            "builtIn": true,
            "authenticationExecutions": [
                {
                    "authenticator": "idp-username-password-form",
                    "authenticatorFlow": false,
                    "requirement": "REQUIRED",
                    "priority": 10,
                    "autheticatorFlow": false,
                    "userSetupAllowed": false
                },
                {
                    "authenticatorFlow": true,
                    "requirement": "CONDITIONAL",
                    "priority": 20,
                    "autheticatorFlow": true,
                    "flowAlias": "First broker login - Conditional OTP",
                    "userSetupAllowed": false
                }
            ]
        },
        {
            "id": "ebc12f73-f393-4506-930f-7a94021aeee8",
            "alias": "browser",
            "description": "Browser based authentication",
            "providerId": "basic-flow",
            "topLevel": true,
            "builtIn": true,
            "authenticationExecutions": [
                {
                    "authenticator": "auth-cookie",
                    "authenticatorFlow": false,
                    "requirement": "ALTERNATIVE",
                    "priority": 10,
                    "autheticatorFlow": false,
                    "userSetupAllowed": false
                },
                {
                    "authenticator": "auth-spnego",
                    "authenticatorFlow": false,
                    "requirement": "DISABLED",
                    "priority": 20,
                    "autheticatorFlow": false,
                    "userSetupAllowed": false
                },
                {
                    "authenticator": "identity-provider-redirector",
                    "authenticatorFlow": false,
                    "requirement": "ALTERNATIVE",
                    "priority": 25,
                    "autheticatorFlow": false,
                    "userSetupAllowed": false
                },
                {
                    "authenticatorFlow": true,
                    "requirement": "ALTERNATIVE",
                    "priority": 26,
                    "autheticatorFlow": true,
                    "flowAlias": "Organization",
                    "userSetupAllowed": false
                },
                {
                    "authenticatorFlow": true,
                    "requirement": "ALTERNATIVE",
                    "priority": 30,
                    "autheticatorFlow": true,
                    "flowAlias": "forms",
                    "userSetupAllowed": false
                }
            ]
        },
        {
            "id": "139260c5-a39d-4505-b293-d24093fca84e",
            "alias": "clients",
            "description": "Base authentication for clients",
            "providerId": "client-flow",
            "topLevel": true,
            "builtIn": true,
            "authenticationExecutions": [
                {
                    "authenticator": "client-secret",
                    "authenticatorFlow": false,
                    "requirement": "ALTERNATIVE",
                    "priority": 10,
                    "autheticatorFlow": false,
                    "userSetupAllowed": false
                },
                {
                    "authenticator": "client-jwt",
                    "authenticatorFlow": false,
                    "requirement": "ALTERNATIVE",
                    "priority": 20,
                    "autheticatorFlow": false,
                    "userSetupAllowed": false
                },
                {
                    "authenticator": "client-secret-jwt",
                    "authenticatorFlow": false,
                    "requirement": "ALTERNATIVE",
                    "priority": 30,
                    "autheticatorFlow": false,
                    "userSetupAllowed": false
                },
                {
                    "authenticator": "client-x509",
                    "authenticatorFlow": false,
                    "requirement": "ALTERNATIVE",
                    "priority": 40,
                    "autheticatorFlow": false,
                    "userSetupAllowed": false
                }
            ]
        },
        {
            "id": "1349be9e-bee1-4885-882f-4f77c7d81b8c",
            "alias": "direct grant",
            "description": "OpenID Connect Resource Owner Grant",
            "providerId": "basic-flow",
            "topLevel": true,
            "builtIn": true,
            "authenticationExecutions": [
                {
                    "authenticator": "direct-grant-validate-username",
                    "authenticatorFlow": false,
                    "requirement": "REQUIRED",
                    "priority": 10,
                    "autheticatorFlow": false,
                    "userSetupAllowed": false
                },
                {
                    "authenticator": "direct-grant-validate-password",
                    "authenticatorFlow": false,
                    "requirement": "REQUIRED",
                    "priority": 20,
                    "autheticatorFlow": false,
                    "userSetupAllowed": false
                },
                {
                    "authenticatorFlow": true,
                    "requirement": "CONDITIONAL",
                    "priority": 30,
                    "autheticatorFlow": true,
                    "flowAlias": "Direct Grant - Conditional OTP",
                    "userSetupAllowed": false
                }
            ]
        },
        {
            "id": "7f298d0e-fce4-4e76-ab0e-6f369a2b69f2",
            "alias": "docker auth",
            "description": "Used by Docker clients to authenticate against the IDP",
            "providerId": "basic-flow",
            "topLevel": true,
            "builtIn": true,
            "authenticationExecutions": [
                {
                    "authenticator": "docker-http-basic-authenticator",
                    "authenticatorFlow": false,
                    "requirement": "REQUIRED",
                    "priority": 10,
                    "autheticatorFlow": false,
                    "userSetupAllowed": false
                }
            ]
        },
        {
            "id": "c5c0ccb4-d387-479f-8f81-999b102d113e",
            "alias": "first broker login",
            "description": "Actions taken after first broker login with identity provider account, which is not yet linked to any Keycloak account",
            "providerId": "basic-flow",
            "topLevel": true,
            "builtIn": true,
            "authenticationExecutions": [
                {
                    "authenticatorConfig": "review profile config",
                    "authenticator": "idp-review-profile",
                    "authenticatorFlow": false,
                    "requirement": "REQUIRED",
                    "priority": 10,
                    "autheticatorFlow": false,
                    "userSetupAllowed": false
                },
                {
                    "authenticatorFlow": true,
                    "requirement": "REQUIRED",
                    "priority": 20,
                    "autheticatorFlow": true,
                    "flowAlias": "User creation or linking",
                    "userSetupAllowed": false
                },
                {
                    "authenticatorFlow": true,
                    "requirement": "CONDITIONAL",
                    "priority": 50,
                    "autheticatorFlow": true,
                    "flowAlias": "First Broker Login - Conditional Organization",
                    "userSetupAllowed": false
                }
            ]
        },
        {
            "id": "fb75d1e9-13b5-4164-a8bd-8f1b9db5b741",
            "alias": "forms",
            "description": "Username, password, otp and other auth forms.",
            "providerId": "basic-flow",
            "topLevel": false,
            "builtIn": true,
            "authenticationExecutions": [
                {
                    "authenticator": "auth-username-password-form",
                    "authenticatorFlow": false,
                    "requirement": "REQUIRED",
                    "priority": 10,
                    "autheticatorFlow": false,
                    "userSetupAllowed": false
                },
                {
                    "authenticatorFlow": true,
                    "requirement": "CONDITIONAL",
                    "priority": 20,
                    "autheticatorFlow": true,
                    "flowAlias": "Browser - Conditional OTP",
                    "userSetupAllowed": false
                }
            ]
        },
        {
            "id": "4b1c0b03-1577-4c57-b3a4-24d968709c69",
            "alias": "registration",
            "description": "Registration flow",
            "providerId": "basic-flow",
            "topLevel": true,
            "builtIn": true,
            "authenticationExecutions": [
                {
                    "authenticator": "registration-page-form",
                    "authenticatorFlow": true,
                    "requirement": "REQUIRED",
                    "priority": 10,
                    "autheticatorFlow": true,
                    "flowAlias": "registration form",
                    "userSetupAllowed": false
                }
            ]
        },
        {
            "id": "2f4d2c00-b417-4957-a0ec-061b3990841d",
            "alias": "registration form",
            "description": "Registration form",
            "providerId": "form-flow",
            "topLevel": false,
            "builtIn": true,
            "authenticationExecutions": [
                {
                    "authenticator": "registration-user-creation",
                    "authenticatorFlow": false,
                    "requirement": "REQUIRED",
                    "priority": 20,
                    "autheticatorFlow": false,
                    "userSetupAllowed": false
                },
                {
                    "authenticator": "registration-password-action",
                    "authenticatorFlow": false,
                    "requirement": "REQUIRED",
                    "priority": 50,
                    "autheticatorFlow": false,
                    "userSetupAllowed": false
                },
                {
                    "authenticator": "registration-recaptcha-action",
                    "authenticatorFlow": false,
                    "requirement": "DISABLED",
                    "priority": 60,
                    "autheticatorFlow": false,
                    "userSetupAllowed": false
                },
                {
                    "authenticator": "registration-terms-and-conditions",
                    "authenticatorFlow": false,
                    "requirement": "DISABLED",
                    "priority": 70,
                    "autheticatorFlow": false,
                    "userSetupAllowed": false
                }
            ]
        },
        {
            "id": "a1e81af1-da96-4080-af36-d3688ca4017d",
            "alias": "reset credentials",
            "description": "Reset credentials for a user if they forgot their password or something",
            "providerId": "basic-flow",
            "topLevel": true,
            "builtIn": true,
            "authenticationExecutions": [
                {
                    "authenticator": "reset-credentials-choose-user",
                    "authenticatorFlow": false,
                    "requirement": "REQUIRED",
                    "priority": 10,
                    "autheticatorFlow": false,
                    "userSetupAllowed": false
                },
                {
                    "authenticator": "reset-credential-email",
                    "authenticatorFlow": false,
                    "requirement": "REQUIRED",
                    "priority": 20,
                    "autheticatorFlow": false,
                    "userSetupAllowed": false
                },
                {
                    "authenticator": "reset-password",
                    "authenticatorFlow": false,
                    "requirement": "REQUIRED",
                    "priority": 30,
                    "autheticatorFlow": false,
                    "userSetupAllowed": false
                },
                {
                    "authenticatorFlow": true,
                    "requirement": "CONDITIONAL",
                    "priority": 40,
                    "autheticatorFlow": true,
                    "flowAlias": "Reset - Conditional OTP",
                    "userSetupAllowed": false
                }
            ]
        },
        {
            "id": "4022acb6-fbc4-4152-b772-8cedb0db9855",
            "alias": "saml ecp",
            "description": "SAML ECP Profile Authentication Flow",
            "providerId": "basic-flow",
            "topLevel": true,
            "builtIn": true,
            "authenticationExecutions": [
                {
                    "authenticator": "http-basic-authenticator",
                    "authenticatorFlow": false,
                    "requirement": "REQUIRED",
                    "priority": 10,
                    "autheticatorFlow": false,
                    "userSetupAllowed": false
                }
            ]
        }
    ],
    "authenticatorConfig": [
        {
            "id": "f5875691-953e-4d63-afd0-12551d325118",
            "alias": "create unique user config",
            "config": {
                "require.password.update.after.registration": "false"
            }
        },
        {
            "id": "76d4cd1c-0b74-4f98-95f2-fe89a243ece1",
            "alias": "review profile config",
            "config": {
                "update.profile.on.first.login": "missing"
            }
        }
    ],
    "requiredActions": [
        {
            "alias": "CONFIGURE_TOTP",
            "name": "Configure OTP",
            "providerId": "CONFIGURE_TOTP",
            "enabled": true,
            "defaultAction": false,
            "priority": 10,
            "config": {}
        },
        {
            "alias": "TERMS_AND_CONDITIONS",
            "name": "Terms and Conditions",
            "providerId": "TERMS_AND_CONDITIONS",
            "enabled": false,
            "defaultAction": false,
            "priority": 20,
            "config": {}
        },
        {
            "alias": "UPDATE_PASSWORD",
            "name": "Update Password",
            "providerId": "UPDATE_PASSWORD",
            "enabled": true,
            "defaultAction": false,
            "priority": 30,
            "config": {}
        },
        {
            "alias": "UPDATE_PROFILE",
            "name": "Update Profile",
            "providerId": "UPDATE_PROFILE",
            "enabled": true,
            "defaultAction": false,
            "priority": 40,
            "config": {}
        },
        {
            "alias": "VERIFY_EMAIL",
            "name": "Verify Email",
            "providerId": "VERIFY_EMAIL",
            "enabled": true,
            "defaultAction": false,
            "priority": 50,
            "config": {}
        },
        {
            "alias": "delete_account",
            "name": "Delete Account",
            "providerId": "delete_account",
            "enabled": false,
            "defaultAction": false,
            "priority": 60,
            "config": {}
        },
        {
            "alias": "webauthn-register",
            "name": "Webauthn Register",
            "providerId": "webauthn-register",
            "enabled": true,
            "defaultAction": false,
            "priority": 70,
            "config": {}
        },
        {
            "alias": "webauthn-register-passwordless",
            "name": "Webauthn Register Passwordless",
            "providerId": "webauthn-register-passwordless",
            "enabled": true,
            "defaultAction": false,
            "priority": 80,
            "config": {}
        },
        {
            "alias": "VERIFY_PROFILE",
            "name": "Verify Profile",
            "providerId": "VERIFY_PROFILE",
            "enabled": true,
            "defaultAction": false,
            "priority": 90,
            "config": {}
        },
        {
            "alias": "delete_credential",
            "name": "Delete Credential",
            "providerId": "delete_credential",
            "enabled": true,
            "defaultAction": false,
            "priority": 100,
            "config": {}
        },
        {
            "alias": "update_user_locale",
            "name": "Update User Locale",
            "providerId": "update_user_locale",
            "enabled": true,
            "defaultAction": false,
            "priority": 1000,
            "config": {}
        }
    ],
    "browserFlow": "browser",
    "registrationFlow": "registration",
    "directGrantFlow": "direct grant",
    "resetCredentialsFlow": "reset credentials",
    "clientAuthenticationFlow": "clients",
    "dockerAuthenticationFlow": "docker auth",
    "firstBrokerLoginFlow": "first broker login",
    "attributes": {
        "cibaBackchannelTokenDeliveryMode": "poll",
        "cibaExpiresIn": "120",
        "cibaAuthRequestedUserHint": "login_hint",
        "oauth2DeviceCodeLifespan": "600",
        "oauth2DevicePollingInterval": "5",
        "parRequestUriLifespan": "60",
        "cibaInterval": "5",
        "realmReusableOtpCode": "false"
    },
    "keycloakVersion": "26.2.5",
    "userManagedAccessAllowed": false,
    "organizationsEnabled": false,
    "verifiableCredentialsEnabled": false,
    "adminPermissionsEnabled": false,
    "clientProfiles": {
        "profiles": []
    },
    "clientPolicies": {
        "policies": []
    }
}
